AUTHORS
CHANGELOG.rst
LICENSE.txt
MANIFEST.in
README.rst
formaldehyde-logo.png
setup.py
django_formaldehyde.egg-info/PKG-INFO
django_formaldehyde.egg-info/SOURCES.txt
django_formaldehyde.egg-info/dependency_links.txt
django_formaldehyde.egg-info/requires.txt
django_formaldehyde.egg-info/top_level.txt
docs/index.rst
formaldehyde/__init__.py
formaldehyde/__init__.pyc
formaldehyde/conf.py
formaldehyde/conf.pyc
formaldehyde/fieldsets.py
formaldehyde/fieldsets.pyc
formaldehyde/readonly.py
formaldehyde/readonly.pyc
formaldehyde/whitespace.py
formaldehyde/whitespace.pyc
formaldehyde/tests/__init__.py
formaldehyde/tests/__init__.pyc
formaldehyde/tests/settings.py
formaldehyde/tests/settings.pyc
formaldehyde/tests/test.py
formaldehyde/tests/test.pyc
formaldehyde/tests/urls.py