Metadata-Version: 1.1
Name: django-formaldehyde
Version: 0.2
Summary: Django forms at warp speed.
Home-page: https://github.com/kunitoki/django-formaldehyde
Author: Lucio Asnaghi (aka kunitoki)
Author-email: kunitoki@gmail.com
License: MIT
Keywords: django,form,formset
Platform: UNKNOWN
Classifier: Development Status :: 4 - Beta
Classifier: Framework :: Django
Classifier: License :: OSI Approved :: MIT License
Classifier: Intended Audience :: Developers
Classifier: Operating System :: OS Independent
Classifier: Programming Language :: Python
Classifier: Programming Language :: Python :: 2.7
Classifier: Programming Language :: Python :: 3.2
Classifier: Programming Language :: Python :: 3.3
Classifier: Programming Language :: Python :: 3.4
Classifier: Environment :: Web Environment
Classifier: Topic :: Software Development
